.DS_Store
.dockerignore
.env.example
.git/FETCH_HEAD
.git/HEAD
.git/config
.git/description
.git/hooks/applypatch-msg.sample
.git/hooks/commit-msg.sample
.git/hooks/fsmonitor-watchman.sample
.git/hooks/post-update.sample
.git/hooks/pre-applypatch.sample
.git/hooks/pre-commit.sample
.git/hooks/pre-merge-commit.sample
.git/hooks/pre-push.sample
.git/hooks/pre-rebase.sample
.git/hooks/pre-receive.sample
.git/hooks/prepare-commit-msg.sample
.git/hooks/push-to-checkout.sample
.git/hooks/update.sample
.git/index
.git/info/exclude
.git/logs/HEAD
.git/logs/refs/heads/main
.git/logs/refs/remotes/origin/main
.git/objects/pack/pack-7a46a14b7f6010d9f04a683130b1bb9a5c0f3637.idx
.git/objects/pack/pack-7a46a14b7f6010d9f04a683130b1bb9a5c0f3637.pack
.git/refs/heads/main
.git/refs/remotes/origin/main
.git/shallow
.github/workflows/jobs.yml
.gitignore
CODE_OF_CONDUCT.md
CONTRIBUTING.md
Doxyfile
ETAPAS.md
LICENSE
Makefile
README.md
data/data_example.csv
data/data_example2.csv
dist/application-gces-2-2022-douglasmonteles-0.2.0.tar.gz
docker/application.Dockerfile
docker/documentation.Dockerfile
docker-compose.yml
docs/.buildinfo
docs/.doctrees/environment.pickle
docs/.doctrees/index.doctree
docs/_sources/index.rst.txt
docs/_static/alabaster.css
docs/_static/basic.css
docs/_static/custom.css
docs/_static/doctools.js
docs/_static/documentation_options.js
docs/_static/file.png
docs/_static/forkme_right_darkblue_121621.png
docs/_static/jquery.js
docs/_static/language_data.js
docs/_static/minus.png
docs/_static/plus.png
docs/_static/pygments.css
docs/_static/searchtools.js
docs/_static/underscore.js
docs/genindex.html
docs/index.html
docs/objects.inv
docs/search.html
docs/searchindex.js
make.bat
metabase/.DS_Store
metabase/config/metabase_database_exemple.env
metabase/config/mongo_exemple.env
metabase/config/postgres_exemple.env
nginx.conf
poetry.lock
pyproject.toml
requirements.txt
scripts/docs.sh
scripts/docs_without_server.sh
scripts/poetry_deploy.sh
scripts/poetry_tests.sh
application_gces_2_2022_douglasmonteles-0.2.0.dist-info/LICENSE
application_gces_2_2022_douglasmonteles-0.2.0.dist-info/WHEEL
application_gces_2_2022_douglasmonteles-0.2.0.dist-info/METADATA
application_gces_2_2022_douglasmonteles-0.2.0.dist-info/RECORD
